mod.py
mod-0.3.0.dist-info/LICENSE
mod-0.3.0.dist-info/METADATA
mod-0.3.0.dist-info/WHEEL
mod-0.3.0.dist-info/top_level.txt
mod-0.3.0.dist-info/zip-safe
mod-0.3.0.dist-info/RECORD
