Metadata-Version: 1.2
Name: mod
Version: 0.3.0
Summary: Modular arithmetic in Python
Home-page: https://github.com/yoeo/mod
Author: Y. SOMDA
License: MIT
Platform: any
Classifier: Development Status :: 4 - Beta
Classifier: Intended Audience :: Developers
Classifier: Intended Audience :: Science/Research
Classifier: License :: OSI Approved :: MIT License
Classifier: Operating System :: OS Independent
Classifier: Programming Language :: Python :: 3
Classifier: Topic :: Scientific/Engineering :: Mathematics
Classifier: Topic :: Software Development :: Libraries :: Python Modules
Requires-Python: >=3
